dedupe/variables/__init__.py
dedupe/variables/fuzzy_category.py
dedupe_variable_fuzzycategory-0.0.1.dist-info/DESCRIPTION.rst
dedupe_variable_fuzzycategory-0.0.1.dist-info/METADATA
dedupe_variable_fuzzycategory-0.0.1.dist-info/RECORD
dedupe_variable_fuzzycategory-0.0.1.dist-info/WHEEL
dedupe_variable_fuzzycategory-0.0.1.dist-info/metadata.json
dedupe_variable_fuzzycategory-0.0.1.dist-info/top_level.txt
