Metadata-Version: 2.0
Name: dedupe-variable-fuzzycategory
Version: 0.0.1
Summary: Fuzzy Categoy variable type for dedupe
Home-page: https://github.com/datamade/dedupe-variables-fuzzycategory
Author: UNKNOWN
Author-email: UNKNOWN
License: The MIT License: http://www.opensource.org/licenses/mit-license.php
Platform: UNKNOWN
Requires-Dist: dedupe
Requires-Dist: future
Requires-Dist: fuzzycategory (>=0.0.4)
